LICENSE
MANIFEST.in
README.rst
VERSION
bin_optimize.py
setup.cfg
setup.py
bin_optimize.egg-info/PKG-INFO
bin_optimize.egg-info/SOURCES.txt
bin_optimize.egg-info/dependency_links.txt
bin_optimize.egg-info/requires.txt
bin_optimize.egg-info/top_level.txt
bin_optimize.egg-info/zip-safe